redcap_eda/__init__.py
redcap_eda/analysis/__init__.py
redcap_eda/analysis/categorical/__init__.py
redcap_eda/analysis/categorical/mixins.py
redcap_eda/analysis/datetime/__init__.py
redcap_eda/analysis/datetime/mixins.py
redcap_eda/analysis/eda.py
redcap_eda/analysis/json_report_handler.py
redcap_eda/analysis/lib.py
redcap_eda/analysis/missing/__init__.py
redcap_eda/analysis/missing/mixins.py
redcap_eda/analysis/numerical/__init__.py
redcap_eda/analysis/numerical/mixins.py
redcap_eda/analysis/text/__init__.py
redcap_eda/analysis/text/mixins.py
redcap_eda/cast_schema.py
redcap_eda/cli.py
redcap_eda/load_case_data.py
redcap_eda/logger.py
redcap_eda/unified_report.py
redcap_eda-0.2.1.dist-info/METADATA
redcap_eda-0.2.1.dist-info/WHEEL
redcap_eda-0.2.1.dist-info/entry_points.txt
redcap_eda-0.2.1.dist-info/RECORD
