Metadata-Version: 2.3
Name: redcap-eda
Version: 0.2.1
Summary: Perform exploratory data analysis on REDCap data
License: MIT
Keywords: redcap,eda,exploratory data analysis,data visualization
Author: Robert Portelli
Requires-Python: >=3.13
Classifier: Development Status :: 4 - Beta
Classifier: Intended Audience :: Developers
Classifier: Intended Audience :: Science/Research
Classifier: License :: OSI Approved :: MIT License
Classifier: Programming Language :: Python
Classifier: Programming Language :: Python :: 3
Classifier: Programming Language :: Python :: 3.10
Classifier: Programming Language :: Python :: 3.11
Classifier: Programming Language :: Python :: 3.12
Classifier: Programming Language :: Python :: 3.13
Classifier: Topic :: Scientific/Engineering :: Information Analysis
Classifier: Topic :: Software Development :: Libraries :: Python Modules
Requires-Dist: click (>=8.1.8,<9.0.0)
Requires-Dist: matplotlib (>=3.10.0,<4.0.0)
Requires-Dist: numpy (>=2.2.3,<3.0.0)
Requires-Dist: pandas (>=2.2.3,<3.0.0)
Requires-Dist: pyyaml (>=6.0.2,<7.0.0)
Requires-Dist: requests (>=2.32.3,<3.0.0)
Requires-Dist: seaborn (>=0.13.2,<1.0.0)
Requires-Dist: tqdm (>=4.67.1,<5.0.0)
Requires-Dist: wordcloud (>=1.9.4,<2.0.0)
Project-URL: Homepage, https://github.com/yourusername/redcap-eda
Project-URL: Repository, https://github.com/yourusername/redcap-eda
Project-URL: issue_tracker, https://github.com/yourusername/redcap-eda/issues
